LICENSE
p115servedb/__init__.py
p115servedb/__main__.py
p115servedb/component/__fuse_monkey_patch.py
p115servedb/component/dav.py
p115servedb/component/db.py
p115servedb/component/fuser.py
p115servedb/component/log.py
p115servedb/dav.py
p115servedb/fuse.py
p115servedb/init.py
p115servedb/py.typed
p115servedb/static/images/close.svg
p115servedb/static/images/fancybox.svg
p115servedb/static/images/favicon.svg
p115servedb/static/images/fileball.svg
p115servedb/static/images/iina.svg
p115servedb/static/images/infuse.svg
p115servedb/static/images/mpv.svg
p115servedb/static/images/mxplayer-pro.svg
p115servedb/static/images/mxplayer.svg
p115servedb/static/images/nplayer.svg
p115servedb/static/images/plyr.svg
p115servedb/static/images/potplayer.svg
p115servedb/static/images/stellarplayer.svg
p115servedb/static/images/subtitle.svg
p115servedb/static/images/vlc.svg
p115servedb/views/base.jinja
p115servedb/views/list.jinja
p115servedb-0.0.6.1.dist-info/LICENSE
p115servedb-0.0.6.1.dist-info/LICENSE_zh
p115servedb-0.0.6.1.dist-info/METADATA
p115servedb-0.0.6.1.dist-info/WHEEL
p115servedb-0.0.6.1.dist-info/entry_points.txt
p115servedb-0.0.6.1.dist-info/RECORD
